lablog/__init__.py
lablog/analyzer.py
lablog/claude_integration.py
lablog/cli.py
lablog/config.py
lablog/context.py
lablog/job_utils.py
lablog/recap.py
lablog/storage.py
lablog/tui.py
lablog-0.1.0.dist-info/licenses/LICENSE
lablog-0.1.0.dist-info/METADATA
lablog-0.1.0.dist-info/WHEEL
lablog-0.1.0.dist-info/entry_points.txt
lablog-0.1.0.dist-info/top_level.txt
lablog-0.1.0.dist-info/RECORD
