Metadata-Version: 2.4
Name: lablog
Version: 0.1.0
Summary: Research workflow memory system - track experiments, todos, and context
Author: Research Community
License: MIT
Project-URL: Homepage, https://github.com/Linskii/lablog
Project-URL: Repository, https://github.com/Linskii/lablog
Project-URL: Issues, https://github.com/Linskii/lablog/issues
Keywords: research,ml,experiment-tracking,workflow,lab-notebook
Classifier: Development Status :: 3 - Alpha
Classifier: Intended Audience :: Science/Research
Classifier: License :: OSI Approved :: MIT License
Classifier: Programming Language :: Python :: 3.9
Classifier: Programming Language :: Python :: 3.10
Classifier: Programming Language :: Python :: 3.11
Classifier: Programming Language :: Python :: 3.12
Requires-Python: >=3.9
License-File: LICENSE
Requires-Dist: click>=8.0.0
Requires-Dist: rich>=13.0.0
Provides-Extra: dev
Requires-Dist: pytest>=7.0.0; extra == "dev"
Requires-Dist: pytest-cov>=4.0.0; extra == "dev"
Dynamic: license-file
